demo/__init__.py
demo/local_settings.py
demo/sass_variables.py
demo/settings.py
demo/urls.py
demo/views.py
demo/wsgi.py
psu_cashnet/__init__.py
psu_cashnet/admin.py
psu_cashnet/apps.py
psu_cashnet/context_processors.py
psu_cashnet/urls.py
psu_cashnet/classes/__init__.py
psu_cashnet/fixtures/__init__.py
psu_cashnet/fixtures/sample_items.yaml
psu_cashnet/migrations/0001_initial.py
psu_cashnet/migrations/0002_auto_20200806_1125.py
psu_cashnet/migrations/0003_auto_20200812_1440.py
psu_cashnet/migrations/0004_auto_20200902_1612.py
psu_cashnet/migrations/0005_purchaseditem_qty.py
psu_cashnet/migrations/0006_auto_20201104_1127.py
psu_cashnet/migrations/0007_auto_20210723_0830.py
psu_cashnet/migrations/0008_auto_20220720_1614.py
psu_cashnet/migrations/__init__.py
psu_cashnet/models/__init__.py
psu_cashnet/models/catalog.py
psu_cashnet/models/purchase.py
psu_cashnet/models/transaction.py
psu_cashnet/services/__init__.py
psu_cashnet/services/cashnet_service.py
psu_cashnet/services/fee_service.py
psu_cashnet/services/transaction_service.py
psu_cashnet/templates/cashnet/cn_downtime.html
psu_cashnet/templates/cashnet/cn_error.html
psu_cashnet/templates/cashnet/catalog/cn_catalog_edit.html
psu_cashnet/templates/cashnet/catalog/cn_catalog_index.html
psu_cashnet/templates/cashnet/emails/safe_template.html
psu_cashnet/templates/cashnet/test/fake_cashnet_site.html
psu_cashnet/templates/cashnet/test/fake_transaction_form.html
psu_cashnet/templates/cashnet/test/fake_tx_failure.html
psu_cashnet/templates/cashnet/test/fake_tx_success.html
psu_cashnet/templates/cashnet/transaction/_cn_tx_object_reference_detail.html
psu_cashnet/templates/cashnet/transaction/_cn_tx_object_reference_list.html
psu_cashnet/templates/cashnet/transaction/cn_transaction_detail.html
psu_cashnet/templates/cashnet/transaction/cn_transaction_index.html
psu_cashnet/templatetags/__init__.py
psu_cashnet/templatetags/cashnet_taglib.py
psu_cashnet/tests/__init__.py
psu_cashnet/tests/test_applications.py
psu_cashnet-2.1.0.dist-info/METADATA
psu_cashnet-2.1.0.dist-info/WHEEL
psu_cashnet-2.1.0.dist-info/top_level.txt
psu_cashnet-2.1.0.dist-info/RECORD
